README.txt
setup.py
src/zdhtmlxscheduler/__init__.py
src/zdhtmlxscheduler.egg-info/PKG-INFO
src/zdhtmlxscheduler.egg-info/SOURCES.txt
src/zdhtmlxscheduler.egg-info/dependency_links.txt
src/zdhtmlxscheduler.egg-info/not-zip-safe
src/zdhtmlxscheduler.egg-info/requires.txt
src/zdhtmlxscheduler.egg-info/top_level.txt