Metadata-Version: 1.0
Name: zdhtmlxscheduler
Version: 1.0.3
Summary: Zope3 Package of DHTMLX Scheduler
Home-page: http://pypi.python.org/pypi/zdhtmlxscheduler
Author: Miano Njoka
Author-email: miano@parliaments.info
License: UNKNOWN
Platform: UNKNOWN
Classifier: Programming Language :: Python
Classifier: Environment :: Web Environment
Classifier: Topic :: Internet :: WWW/HTTP :: WSGI :: Application
Classifier: Framework :: Zope3
